evalgate/__init__.py
evalgate/cli.py
evalgate/config.py
evalgate/report.py
evalgate/store.py
evalgate/templates.py
evalgate/util.py
evalgate/evaluators/category_match.py
evalgate/evaluators/json_schema.py
evalgate/evaluators/latency_cost.py
evalgate/evaluators/llm_judge.py
evalgate/templates/default_config.yml
evalgate/templates/fixture_example.json
evalgate/templates/quality_judge.txt
evalgate/templates/schema_example.json
evalgate/templates/sentiment_judge.txt
evalgate-0.2.0.dist-info/licenses/LICENSE
evalgate-0.2.0.dist-info/METADATA
evalgate-0.2.0.dist-info/WHEEL
evalgate-0.2.0.dist-info/entry_points.txt
evalgate-0.2.0.dist-info/top_level.txt
evalgate-0.2.0.dist-info/RECORD
