Metadata-Version: 2.4
Name: evalgate
Version: 0.2.0
Summary: Deterministic LLM/RAG evals as a PR check
Author-email: AOTP Ventures <team@aotp.ventures>
License: MIT
Project-URL: Homepage, https://evalgate.aotp.ai/
Project-URL: Repository, https://github.com/aotp-ventures/evalgate
Requires-Python: >=3.10
License-File: LICENSE
Requires-Dist: typer>=0.12
Requires-Dist: pydantic>=2.7
Requires-Dist: pyyaml>=6.0
Requires-Dist: jsonschema>=4.21
Requires-Dist: rich>=13.8
Provides-Extra: llm
Requires-Dist: openai>=1.0.0; extra == "llm"
Requires-Dist: anthropic>=0.34.0; extra == "llm"
Provides-Extra: dev
Requires-Dist: pytest>=8.0; extra == "dev"
Requires-Dist: pytest-cov>=4.0; extra == "dev"
Requires-Dist: ruff>=0.1.0; extra == "dev"
Dynamic: license-file
